{
  "contract_version": "1.0.0",
  "definitions": [
    {
      "problem_definition_id": "PROBLEM_QUADRATIC_CONTINUOUS",
      "name_ja": "連続二次最適化",
      "name_en": "Continuous quadratic optimization",
      "mathematical_family": "quadratic",
      "variable_domain": "continuous",
      "objective_form": "quadratic",
      "objective_direction": "minimize",
      "available_oracles": ["objective_value", "gradient", "hessian"],
      "constraint_class": "none",
      "dimensionality_policy": {"kind": "parameterized", "minimum": 1},
      "known_reference_semantics": "Positive-definite instances have one exact global minimizer.",
      "related_problem_ids": ["PA006", "PA018"],
      "feature_ids": ["F_VARIABLE_CONTINUOUS", "F_OBJECTIVE_QUADRATIC", "F_OBJECTIVE_STRONGLY_CONVEX"],
      "source_ids": ["S055", "S056"],
      "last_verified": "2026-07-15"
    },
    {
      "problem_definition_id": "PROBLEM_ROSENBROCK",
      "name_ja": "Rosenbrock谷",
      "name_en": "Rosenbrock valley",
      "mathematical_family": "rosenbrock",
      "variable_domain": "continuous",
      "objective_form": "general_nonlinear",
      "objective_direction": "minimize",
      "available_oracles": ["objective_value", "gradient"],
      "constraint_class": "none",
      "dimensionality_policy": {"kind": "parameterized", "minimum": 2},
      "known_reference_semantics": "The standard instance has an exact global minimizer at the all-ones vector.",
      "related_problem_ids": ["PA006"],
      "feature_ids": ["F_VARIABLE_CONTINUOUS", "F_OBJECTIVE_NONCONVEX", "F_NUMERICAL_NARROW_VALLEY"],
      "source_ids": ["S056", "S063"],
      "last_verified": "2026-07-15"
    },
    {
      "problem_definition_id": "PROBLEM_MULTIMODAL_CONTINUOUS",
      "name_ja": "多峰性連続関数",
      "name_en": "Multimodal continuous function",
      "mathematical_family": "rastrigin",
      "variable_domain": "continuous",
      "objective_form": "general_nonlinear",
      "objective_direction": "minimize",
      "available_oracles": ["objective_value"],
      "constraint_class": "bounds",
      "dimensionality_policy": {"kind": "parameterized", "minimum": 1},
      "known_reference_semantics": "The canonical unshifted test instance has a known exact global minimizer.",
      "related_problem_ids": ["PA012", "PA014"],
      "feature_ids": ["F_OBJECTIVE_MULTIMODAL", "F_NUMERICAL_MANY_LOCAL_OPTIMA", "F_VARIABLE_CONTINUOUS"],
      "source_ids": ["S056"],
      "last_verified": "2026-07-15"
    },
    {
      "problem_definition_id": "PROBLEM_NONSMOOTH_CONTINUOUS",
      "name_ja": "非滑らか連続関数",
      "name_en": "Nonsmooth continuous function",
      "mathematical_family": "absolute_ridge",
      "variable_domain": "continuous",
      "objective_form": "piecewise_linear",
      "objective_direction": "minimize",
      "available_oracles": ["objective_value", "subgradient"],
      "constraint_class": "bounds",
      "dimensionality_policy": {"kind": "fixed", "dimension": 2},
      "known_reference_semantics": "The nonnegative absolute-value terms identify an exact minimizer.",
      "related_problem_ids": ["PA010", "PA011"],
      "feature_ids": ["F_OBJECTIVE_NONSMOOTH", "F_DERIVATIVE_NOT_DIFFERENTIABLE", "F_VARIABLE_CONTINUOUS"],
      "source_ids": ["S055", "S066"],
      "last_verified": "2026-07-15"
    },
    {
      "problem_definition_id": "PROBLEM_EXPENSIVE_BLACK_BOX_1D",
      "name_ja": "高価な1次元black-box",
      "name_en": "Expensive one-dimensional black box",
      "mathematical_family": "wavy_black_box",
      "variable_domain": "continuous",
      "objective_form": "black_box",
      "objective_direction": "minimize",
      "available_oracles": ["objective_value"],
      "constraint_class": "bounds",
      "dimensionality_policy": {"kind": "fixed", "dimension": 1},
      "known_reference_semantics": "The optimizer is not given a reference; the hidden truth is only for educational rendering.",
      "related_problem_ids": ["PA013", "PA014"],
      "feature_ids": ["F_OBJECTIVE_NOISY", "F_EVALUATION_COST", "F_VARIABLE_CONTINUOUS"],
      "source_ids": ["S059", "S075"],
      "last_verified": "2026-07-15"
    },
    {
      "problem_definition_id": "PROBLEM_BINARY_KNAPSACK",
      "name_ja": "0-1 knapsack",
      "name_en": "Binary knapsack",
      "mathematical_family": "binary_knapsack",
      "variable_domain": "binary",
      "objective_form": "linear",
      "objective_direction": "maximize",
      "available_oracles": ["objective_value", "feasibility", "relaxation_bound"],
      "constraint_class": "linear_inequality",
      "dimensionality_policy": {"kind": "parameterized", "minimum": 1},
      "known_reference_semantics": "Small instances can be exhaustively certified; larger instances may use best-known bounds.",
      "related_problem_ids": ["PA023", "PA032"],
      "feature_ids": ["F_STRUCTURE_KNAPSACK", "F_VARIABLE_BINARY", "F_GUARANTEE_BOUNDS"],
      "source_ids": ["S021", "S022", "S079"],
      "last_verified": "2026-07-15"
    },
    {
      "problem_definition_id": "PROBLEM_LINEAR_ASSIGNMENT",
      "name_ja": "線形assignment",
      "name_en": "Linear assignment",
      "mathematical_family": "linear_assignment",
      "variable_domain": "permutation",
      "objective_form": "linear",
      "objective_direction": "minimize",
      "available_oracles": ["objective_value", "feasibility"],
      "constraint_class": "assignment",
      "dimensionality_policy": {"kind": "square_matrix", "minimum": 2},
      "known_reference_semantics": "A finite assignment instance has a certifiable exact optimum.",
      "related_problem_ids": ["PA030"],
      "feature_ids": ["F_STRUCTURE_ASSIGNMENT", "F_VARIABLE_PERMUTATION", "F_OBJECTIVE_LINEAR"],
      "source_ids": ["S054", "S078"],
      "last_verified": "2026-07-15"
    },
    {
      "problem_definition_id": "PROBLEM_CONSTRAINED_CONTINUOUS_2D",
      "name_ja": "制約付き2次元問題",
      "name_en": "Constrained two-dimensional problem",
      "mathematical_family": "constrained_quadratic",
      "variable_domain": "continuous",
      "objective_form": "quadratic",
      "objective_direction": "minimize",
      "available_oracles": ["objective_value", "gradient", "constraint_value", "constraint_jacobian"],
      "constraint_class": "nonlinear_inequality",
      "dimensionality_policy": {"kind": "fixed", "dimension": 2},
      "known_reference_semantics": "The active circular boundary and KKT conditions give an exact reference.",
      "related_problem_ids": ["PA009"],
      "feature_ids": ["F_CONSTRAINT_NONLINEAR_INEQUALITY", "F_OBJECTIVE_QUADRATIC", "F_VARIABLE_CONTINUOUS"],
      "source_ids": ["S055", "S056"],
      "last_verified": "2026-07-15"
    },
    {
      "problem_definition_id": "PROBLEM_NONLINEAR_LEAST_SQUARES",
      "name_ja": "bounds付き非線形最小二乗",
      "name_en": "Bounded nonlinear least squares",
      "mathematical_family": "nonlinear_least_squares",
      "variable_domain": "continuous",
      "objective_form": "sum_of_squared_residuals",
      "objective_direction": "minimize",
      "available_oracles": ["residual_vector", "jacobian", "objective_value", "gradient"],
      "constraint_class": "bounds",
      "dimensionality_policy": {"kind": "fixed", "dimension": 3},
      "known_reference_semantics": "The noiseless synthetic data are generated from the recorded three-parameter truth; this reference is for teaching and validation, not optimizer input.",
      "related_problem_ids": ["PA033"],
      "feature_ids": ["F_STRUCTURE_NONLINEAR_LEAST_SQUARES", "F_VARIABLE_CONTINUOUS", "F_CONSTRAINT_BOUNDS"],
      "source_ids": ["S003", "S041", "S056", "S096"],
      "last_verified": "2026-07-17"
    },
    {
      "problem_definition_id": "PROBLEM_BIOBJECTIVE_CONTINUOUS",
      "name_ja": "2目的連続問題",
      "name_en": "Bi-objective continuous problem",
      "mathematical_family": "biobjective_quadratic",
      "variable_domain": "continuous",
      "objective_form": "multiobjective",
      "objective_direction": "multiobjective",
      "available_oracles": ["objective_vector"],
      "constraint_class": "bounds",
      "dimensionality_policy": {"kind": "fixed", "dimension": 2},
      "known_reference_semantics": "The Pareto set and its objective-space image are available analytically.",
      "related_problem_ids": ["PA038"],
      "feature_ids": ["F_OBJECTIVE_MULTIOBJECTIVE", "F_STRUCTURE_MULTIOBJECTIVE", "F_GUARANTEE_PARETO_SET"],
      "source_ids": ["S039", "S068"],
      "last_verified": "2026-07-15"
    },
    {
      "problem_definition_id": "PROBLEM_TOPOLOGY_OPTIMIZATION",
      "name_ja": "構造トポロジー最適化",
      "name_en": "Structural topology optimization",
      "mathematical_family": "topology_optimization",
      "variable_domain": "field",
      "objective_form": "simulation",
      "objective_direction": "minimize",
      "available_oracles": ["objective_value", "gradient", "constraint_value", "constraint_jacobian"],
      "constraint_class": "integral_volume_fraction",
      "dimensionality_policy": {"kind": "fixed", "dimension": 32},
      "known_reference_semantics": "The educational instance has no exact global reference; the rendered fields are deterministic teaching outputs on a discretized model.",
      "related_problem_ids": ["PA045"],
      "feature_ids": ["F_VARIABLE_FUNCTION", "F_OBJECTIVE_SIMULATION", "F_CONSTRAINT_PDE", "F_CONSTRAINT_LINEAR_INEQUALITY", "F_DERIVATIVE_ANALYTIC_GRADIENT", "F_DERIVATIVE_INNER_ITERATION", "F_STRUCTURE_PDE_CONSTRAINED", "F_GUARANTEE_LOCAL_OK"],
      "source_ids": ["S097", "S098", "S099", "S101"],
      "last_verified": "2026-07-18"
    },
    {
      "problem_definition_id": "PROBLEM_OPTIMAL_CONTROL",
      "name_ja": "離散化された最適制御問題",
      "name_en": "Discretized optimal control problem",
      "mathematical_family": "optimal_control",
      "variable_domain": "trajectory",
      "objective_form": "simulation",
      "objective_direction": "minimize",
      "available_oracles": ["objective_value", "constraint_value"],
      "constraint_class": "dynamics_equality",
      "dimensionality_policy": {"kind": "fixed", "dimension": 60},
      "known_reference_semantics": "The fixed mesh is an educational transcription; continuous-time feasibility and optimality require mesh refinement and trajectory reconstruction.",
      "related_problem_ids": ["PA042", "PA044"],
      "feature_ids": ["F_VARIABLE_TRAJECTORY", "F_CONSTRAINT_DYNAMICS", "F_OBJECTIVE_SIMULATION", "F_STRUCTURE_OPTIMAL_CONTROL"],
      "source_ids": ["S042", "S043", "S050", "S076"],
      "last_verified": "2026-07-19"
    }
  ],
  "instances": [
    {
      "problem_instance_id": "INSTANCE_QUADRATIC_ISOTROPIC_2D",
      "problem_definition_id": "PROBLEM_QUADRATIC_CONTINUOUS",
      "name_ja": "等方的な二次関数",
      "name_en": "Isotropic quadratic",
      "registry_key": "problem.quadratic.isotropic.v1",
      "dimension": 2,
      "parameters": {"weights": [1.0, 1.0]},
      "bounds": {"x": [-4.0, 4.0], "y": [-4.0, 4.0]},
      "constraints": [],
      "initialization_candidates": [{"candidate_id": "default", "point": [-2.5, 2.0]}],
      "seed_status": "not_applicable",
      "seed_value": null,
      "known_reference_status": "known_exact",
      "known_reference": {"point": [0.0, 0.0], "value": 0.0, "source_ids": ["S055"]},
      "display": {"range": {"x": [-4.0, 4.0], "y": [-4.0, 4.0], "z": [0.0, 32.0]}, "axis_labels": ["x", "y", "f(x,y)"], "units": ["dimensionless", "dimensionless", "dimensionless"], "expression": "f(x, y) = x² + y²"},
      "intended_phenomena": ["isotropic_curvature", "radial_level_sets"],
      "limitations_ja": "2次元・無制約・正定値の教育用instanceです。",
      "limitations_en": "A two-dimensional unconstrained positive-definite educational instance.",
      "source_ids": ["S055", "S056"],
      "last_verified": "2026-07-15"
    },
    {
      "problem_instance_id": "OBJECTIVE_QUADRATIC_2D",
      "problem_definition_id": "PROBLEM_QUADRATIC_CONTINUOUS",
      "name_ja": "悪条件の二次関数",
      "name_en": "Ill-conditioned quadratic",
      "registry_key": "problem.quadratic.ill_conditioned.v1",
      "dimension": 2,
      "parameters": {"weights": [100.0, 1.0], "condition_number": 100.0},
      "bounds": {"x": [-4.0, 4.0], "y": [-4.0, 4.0]},
      "constraints": [],
      "initialization_candidates": [{"candidate_id": "first_order_default", "point": [-1.6, 1.6]}, {"candidate_id": "simplex_default", "point": [-2.5, 2.0]}],
      "seed_status": "not_applicable",
      "seed_value": null,
      "known_reference_status": "known_exact",
      "known_reference": {"point": [0.0, 0.0], "value": 0.0, "source_ids": ["S056"]},
      "display": {"range": {"x": [-4.0, 4.0], "y": [-4.0, 4.0], "z": [0.0, 1600.0]}, "axis_labels": ["x", "y", "f(x,y)"], "units": ["dimensionless", "dimensionless", "dimensionless"], "expression": "f(x, y) = 100x² + y²"},
      "intended_phenomena": ["ill_conditioning", "zig_zagging", "momentum_acceleration"],
      "limitations_ja": "固定condition numberの2次元教育用instanceで、一般性能を順位付けしません。",
      "limitations_en": "A fixed-condition-number 2D lesson, not a general performance ranking.",
      "source_ids": ["S001", "S056"],
      "last_verified": "2026-07-15"
    },
    {
      "problem_instance_id": "OBJECTIVE_ROSENBROCK_2D",
      "problem_definition_id": "PROBLEM_ROSENBROCK",
      "name_ja": "2次元Rosenbrock関数",
      "name_en": "Two-dimensional Rosenbrock function",
      "registry_key": "problem.rosenbrock.v1",
      "dimension": 2,
      "parameters": {"a": 1.0, "b": 100.0},
      "bounds": {"x": [-2.0, 2.0], "y": [-1.0, 3.0]},
      "constraints": [],
      "initialization_candidates": [{"candidate_id": "default", "point": [-1.2, 1.0]}, {"candidate_id": "shrink_demo", "point": [-2.0, -1.0]}],
      "seed_status": "not_applicable",
      "seed_value": null,
      "known_reference_status": "known_exact",
      "known_reference": {"point": [1.0, 1.0], "value": 0.0, "source_ids": ["S056"]},
      "display": {"range": {"x": [-2.0, 2.0], "y": [-1.0, 3.0], "z": [0.0, 2500.0]}, "axis_labels": ["x", "y", "f(x,y)"], "units": ["dimensionless", "dimensionless", "dimensionless"], "expression": "f(x, y) = 100(y - x²)² + (1 - x)²"},
      "intended_phenomena": ["narrow_curved_valley", "initialization_sensitivity", "simplex_shrink"],
      "limitations_ja": "2次元の標準係数だけを扱います。",
      "limitations_en": "Only the standard two-dimensional coefficients are represented.",
      "source_ids": ["S056", "S063"],
      "last_verified": "2026-07-15"
    },
    {
      "problem_instance_id": "INSTANCE_RASTRIGIN_2D",
      "problem_definition_id": "PROBLEM_MULTIMODAL_CONTINUOUS",
      "name_ja": "2次元Rastrigin関数",
      "name_en": "Two-dimensional Rastrigin function",
      "registry_key": "problem.rastrigin.v1",
      "dimension": 2,
      "parameters": {"amplitude": 10.0},
      "bounds": {"x": [-5.12, 5.12], "y": [-5.12, 5.12]},
      "constraints": [],
      "initialization_candidates": [{"candidate_id": "default", "point": [3.5, -2.5]}],
      "seed_status": "not_applicable",
      "seed_value": null,
      "known_reference_status": "known_exact",
      "known_reference": {"point": [0.0, 0.0], "value": 0.0, "source_ids": ["S056"]},
      "display": {"range": {"x": [-5.12, 5.12], "y": [-5.12, 5.12], "z": [0.0, 80.0]}, "axis_labels": ["x", "y", "f(x,y)"], "units": ["dimensionless", "dimensionless", "dimensionless"], "expression": "f(x)=20+Σ(xᵢ²-10 cos(2πxᵢ))"},
      "intended_phenomena": ["many_local_minima", "global_search"],
      "limitations_ja": "標準のunshifted 2次元test functionです。",
      "limitations_en": "The standard unshifted two-dimensional test function.",
      "source_ids": ["S056"],
      "last_verified": "2026-07-15"
    },
    {
      "problem_instance_id": "INSTANCE_ABSOLUTE_RIDGE_2D",
      "problem_definition_id": "PROBLEM_NONSMOOTH_CONTINUOUS",
      "name_ja": "絶対値ridge",
      "name_en": "Absolute-value ridge",
      "registry_key": "problem.absolute_ridge.v1",
      "dimension": 2,
      "parameters": {"weights": [1.0, 2.0], "coupling": 0.25},
      "bounds": {"x": [-4.0, 4.0], "y": [-4.0, 4.0]},
      "constraints": [],
      "initialization_candidates": [{"candidate_id": "default", "point": [-3.0, 2.0]}],
      "seed_status": "not_applicable",
      "seed_value": null,
      "known_reference_status": "known_exact",
      "known_reference": {"point": [0.0, 0.0], "value": 0.0, "source_ids": ["S055"]},
      "display": {"range": {"x": [-4.0, 4.0], "y": [-4.0, 4.0], "z": [0.0, 30.0]}, "axis_labels": ["x", "y", "f(x,y)"], "units": ["dimensionless", "dimensionless", "dimensionless"], "expression": "f(x,y)=|x|+2|y|+0.25|x-y|"},
      "intended_phenomena": ["nondifferentiable_kink", "subgradient_set"],
      "limitations_ja": "低次元の凸piecewise-linear例で、一般の非滑らか非凸問題ではありません。",
      "limitations_en": "A low-dimensional convex piecewise-linear example, not a general nonsmooth nonconvex problem.",
      "source_ids": ["S055", "S066"],
      "last_verified": "2026-07-15"
    },
    {
      "problem_instance_id": "OBJECTIVE_EDUCATIONAL_WAVY_1D",
      "problem_definition_id": "PROBLEM_EXPENSIVE_BLACK_BOX_1D",
      "name_ja": "波状1次元black-box",
      "name_en": "Wavy one-dimensional black box",
      "registry_key": "problem.wavy_black_box.v1",
      "dimension": 1,
      "parameters": {"noise_presets": {"noiseless": 0.0, "small_noise": 0.08}, "hidden_truth_for_renderer": true},
      "bounds": {"x": [-3.0, 3.0]},
      "constraints": [],
      "initialization_candidates": [{"candidate_id": "bo_initial_design", "point": [-2.6, 0.0, 2.6]}],
      "seed_status": "fixed",
      "seed_value": 2604,
      "known_reference_status": "unknown",
      "known_reference": null,
      "display": {"range": {"x": [-3.0, 3.0], "y": [-1.0, 3.0]}, "axis_labels": ["x", "observed objective"], "units": ["dimensionless", "dimensionless"], "expression": "0.16(x-1.7)² + 0.45 sin(2.2x) + 0.12 sin(5.3x)"},
      "intended_phenomena": ["surrogate_uncertainty", "exploration_exploitation", "observation_noise"],
      "limitations_ja": "hidden truthは教材表示だけに使い、optimizerへ既知最適解として渡しません。",
      "limitations_en": "The hidden truth is only rendered for teaching and is not supplied to the optimizer as a known optimum.",
      "source_ids": ["S059", "S075"],
      "last_verified": "2026-07-15"
    },
    {
      "problem_instance_id": "INSTANCE_BINARY_KNAPSACK_4",
      "problem_definition_id": "PROBLEM_BINARY_KNAPSACK",
      "name_ja": "4品目0-1 knapsack",
      "name_en": "Four-item binary knapsack",
      "registry_key": "problem.knapsack.binary.v1",
      "dimension": 4,
      "parameters": {"capacity": 7, "items": [{"item_id": "A", "weight": 4, "value": 9}, {"item_id": "B", "weight": 3, "value": 6}, {"item_id": "D", "weight": 2, "value": 4}, {"item_id": "C", "weight": 3, "value": 5}]},
      "bounds": {"variables": [[0, 1], [0, 1], [0, 1], [0, 1]]},
      "constraints": [{"constraint_id": "capacity", "sense": "lte", "rhs": 7}],
      "initialization_candidates": [{"candidate_id": "empty", "assignment": [0, 0, 0, 0]}, {"candidate_id": "heuristic", "assignment": [1, 0, 1, 0]}],
      "seed_status": "fixed",
      "seed_value": 0,
      "known_reference_status": "known_exact",
      "known_reference": {"assignment": [1, 1, 0, 0], "value": 15, "weight": 7, "source_ids": ["S021", "S022"]},
      "display": {"range": {"depth": [0, 4], "objective": [0, 15], "bound": [0, 17]}, "axis_labels": ["search depth", "objective/bound"], "units": ["items", "value"], "expression": "max 9A+6B+4D+5C; 4A+3B+2D+3C≤7"},
      "intended_phenomena": ["branch_and_bound", "incumbent", "bound_pruning", "optimality_certificate"],
      "limitations_ja": "4品目の教育用instanceで、大規模MIP性能を表しません。",
      "limitations_en": "A four-item educational instance, not a large-scale MIP benchmark.",
      "source_ids": ["S021", "S022", "S079"],
      "last_verified": "2026-07-15"
    },
    {
      "problem_instance_id": "INSTANCE_ASSIGNMENT_3X3",
      "problem_definition_id": "PROBLEM_LINEAR_ASSIGNMENT",
      "name_ja": "3×3 assignment",
      "name_en": "Three-by-three assignment",
      "registry_key": "problem.assignment.linear.v1",
      "dimension": 3,
      "parameters": {"cost_matrix": [[4, 1, 3], [2, 0, 5], [3, 2, 2]]},
      "bounds": {"assignment_columns": [0, 1, 2]},
      "constraints": [{"constraint_id": "permutation", "type": "all_different"}],
      "initialization_candidates": [{"candidate_id": "identity", "assignment": [0, 1, 2]}],
      "seed_status": "not_applicable",
      "seed_value": null,
      "known_reference_status": "known_exact",
      "known_reference": {"assignment": [1, 0, 2], "value": 5, "source_ids": ["S054"]},
      "display": {"range": {"cost": [0, 12]}, "axis_labels": ["worker", "task", "cost"], "units": ["index", "index", "cost"], "expression": "min Σ cᵢⱼ xᵢⱼ"},
      "intended_phenomena": ["one_to_one_matching", "combinatorial_feasibility"],
      "limitations_ja": "小さなdense cost matrixで、禁止辺やrectangular assignmentを含みません。",
      "limitations_en": "A small dense cost matrix without forbidden edges or rectangular assignment.",
      "source_ids": ["S054", "S078"],
      "last_verified": "2026-07-15"
    },
    {
      "problem_instance_id": "INSTANCE_CONSTRAINED_DISK_2D",
      "problem_definition_id": "PROBLEM_CONSTRAINED_CONTINUOUS_2D",
      "name_ja": "円内制約付き二次関数",
      "name_en": "Quadratic inside a disk",
      "registry_key": "problem.constrained_disk.v1",
      "dimension": 2,
      "parameters": {"circle_center": [1.0, 1.0], "circle_radius": 1.0},
      "bounds": {"x": [-1.0, 3.0], "y": [-1.0, 3.0]},
      "constraints": [{"constraint_id": "inside_disk", "expression": "(x-1)^2+(y-1)^2 <= 1", "sense": "lte", "rhs": 1.0}],
      "initialization_candidates": [{"candidate_id": "feasible", "point": [1.0, 1.0]}, {"candidate_id": "infeasible", "point": [2.0, 2.0]}],
      "seed_status": "not_applicable",
      "seed_value": null,
      "known_reference_status": "known_exact",
      "known_reference": {"point": [0.2928932188134524, 0.2928932188134524], "value": 0.1715728752538099, "active_constraints": ["inside_disk"], "source_ids": ["S055"]},
      "display": {"range": {"x": [-1.0, 3.0], "y": [-1.0, 3.0], "z": [0.0, 18.0]}, "axis_labels": ["x", "y", "f(x,y)"], "units": ["dimensionless", "dimensionless", "dimensionless"], "expression": "min x²+y² s.t. (x-1)²+(y-1)²≤1"},
      "intended_phenomena": ["feasible_region", "active_constraint", "constraint_violation"],
      "limitations_ja": "単一の凸feasible setを持つ2次元教材です。",
      "limitations_en": "A two-dimensional lesson with one convex feasible set.",
      "source_ids": ["S055", "S056"],
      "last_verified": "2026-07-15"
    },
    {
      "problem_instance_id": "INSTANCE_EXPONENTIAL_DECAY_FIT_3P",
      "problem_definition_id": "PROBLEM_NONLINEAR_LEAST_SQUARES",
      "name_ja": "3 parameter指数減衰fit",
      "name_en": "Three-parameter exponential-decay fit",
      "registry_key": "problem.nonlinear_least_squares.exponential_decay.v1",
      "dimension": 3,
      "parameters": {"time_points": {"start": 0.0, "stop": 5.0, "count": 20}, "truth": [1.8, 0.7, 0.25], "model": "a*exp(-k*t)+c", "noise": 0.0},
      "bounds": {"lower": [0.0, 0.0, -1.0], "upper": [5.0, 3.0, 2.0], "parameter_names": ["a", "k", "c"]},
      "constraints": [{"constraint_id": "parameter_bounds", "type": "bounds", "lower": [0.0, 0.0, -1.0], "upper": [5.0, 3.0, 2.0]}],
      "initialization_candidates": [{"candidate_id": "normal", "point": [1.0, 0.4, 0.0]}, {"candidate_id": "poor_rank", "point": [0.0, 2.5, 0.25]}],
      "seed_status": "not_applicable",
      "seed_value": null,
      "known_reference_status": "known_exact",
      "known_reference": {"point": [1.8, 0.7, 0.25], "value": 0.0, "source_ids": ["S056"]},
      "display": {"range": {"time": [0.0, 5.0], "response": [0.0, 2.2], "residual_norm": [0.0, 4.0]}, "axis_labels": ["time", "response", "residual norm"], "units": ["dimensionless", "dimensionless", "dimensionless"], "expression": "min Σᵢ(a exp(-k tᵢ)+c-yᵢ)², 0≤a≤5, 0≤k≤3, -1≤c≤2"},
      "intended_phenomena": ["residual_structure", "jacobian_rank", "initialization_sensitivity", "bounded_fit"],
      "limitations_ja": "20点・noiseなしの合成dataを使う3 parameter教材です。実dataの識別性、外れ値、誤差model、scaleを代表しません。",
      "limitations_en": "A three-parameter lesson on 20 noiseless synthetic observations; it does not represent real-data identifiability, outliers, error models, or scaling.",
      "source_ids": ["S003", "S041", "S056", "S096"],
      "last_verified": "2026-07-17"
    },
    {
      "problem_instance_id": "INSTANCE_BIOBJECTIVE_QUADRATIC_2D",
      "problem_definition_id": "PROBLEM_BIOBJECTIVE_CONTINUOUS",
      "name_ja": "競合する2つの二次目的",
      "name_en": "Two competing quadratic objectives",
      "registry_key": "problem.biobjective_quadratic.v1",
      "dimension": 2,
      "parameters": {"centers": [[0.0, 0.0], [2.0, 2.0]]},
      "bounds": {"x": [0.0, 2.0], "y": [0.0, 2.0]},
      "constraints": [],
      "initialization_candidates": [{"candidate_id": "center", "point": [1.0, 1.0]}],
      "seed_status": "not_applicable",
      "seed_value": null,
      "known_reference_status": "known_exact",
      "known_reference": {"pareto_set": {"parameter": "t", "point": ["t", "t"], "range": [0.0, 2.0]}, "objective_endpoints": [[0.0, 8.0], [8.0, 0.0]], "source_ids": ["S039", "S068"]},
      "display": {"range": {"decision_x": [0.0, 2.0], "decision_y": [0.0, 2.0], "objective_1": [0.0, 8.0], "objective_2": [0.0, 8.0]}, "axis_labels": ["f₁", "f₂"], "units": ["dimensionless", "dimensionless"], "expression": "f₁=x²+y²; f₂=(x-2)²+(y-2)²"},
      "intended_phenomena": ["pareto_front", "tradeoff", "nondominance"],
      "limitations_ja": "凸で解析的な2目的教材で、disconnected Pareto frontを表しません。",
      "limitations_en": "A convex analytic bi-objective lesson without disconnected Pareto fronts.",
      "source_ids": ["S039", "S068"],
      "last_verified": "2026-07-15"
    },
    {
      "problem_instance_id": "INSTANCE_TOPOLOGY_CANTILEVER_2D",
      "problem_definition_id": "PROBLEM_TOPOLOGY_OPTIMIZATION",
      "name_ja": "片持ちはりの最小compliance",
      "name_en": "Cantilever minimum-compliance topology optimization",
      "registry_key": "problem.topology.cantilever.v1",
      "dimension": 32,
      "parameters": {"grid": {"columns": 8, "rows": 4}, "volume_fraction": 0.5, "penalization": 3.0, "youngs_modulus": 1.0, "minimum_modulus": 0.001, "filter_radius": 1.5, "projection_beta": 8.0, "reference_generator": "educational.topology_optimization.v1"},
      "bounds": {"density": [0.001, 1.0]},
      "constraints": [{"constraint_id": "volume_fraction", "expression": "mean(ρ) ≤ 0.5", "sense": "lte", "rhs": 0.5}],
      "initialization_candidates": [{"candidate_id": "uniform_half", "density": 0.5}],
      "seed_status": "not_applicable",
      "seed_value": null,
      "known_reference_status": "not_meaningful",
      "known_reference": null,
      "display": {"range": {"density": [0.0, 1.0], "compliance": [0.0, 80.0]}, "axis_labels": ["element x", "element y", "density/compliance"], "units": ["element", "element", "normalized"], "expression": "min c(ρ)=Fᵀu, K(ρ)u=F, Eₑ=Emin+ρₑᵖ(E₀−Emin), mean(ρ)≤0.5"},
      "intended_phenomena": ["field_valued_design", "state_solve", "adjoint_sensitivity", "density_filter", "optimality_criteria", "gray_density", "checkerboard", "mesh_dependence"],
      "limitations_ja": "8×4要素の決定的な教育用instanceです。FEM方程式、filter、projection、OC/MMAの役割を追うためのreferenceであり、実設計の強度・座屈・製造性・連続体の保証や一般性能を示しません。",
      "limitations_en": "A deterministic 8x4 educational instance for following the FEM state equation, filtering, projection, and OC/MMA roles; it does not establish real-design strength, buckling, manufacturability, continuous-model guarantees, or general performance.",
      "source_ids": ["S097", "S098", "S099", "S100", "S101"],
      "last_verified": "2026-07-18"
    },
    {
      "problem_instance_id": "INSTANCE_OPTIMAL_CONTROL_EC020",
      "problem_definition_id": "PROBLEM_OPTIMAL_CONTROL",
      "name_ja": "EC020 二次系の軌道・制御",
      "name_en": "EC020 trajectory and control for a second-order system",
      "registry_key": "problem.optimal_control.ec020.v1",
      "dimension": 60,
      "parameters": {"mesh_intervals": 20, "state_dimension": 2, "control_dimension": 1, "dynamics": "x_dot=v; v_dot=u", "running_weights": {"state": 1.0, "control": 0.01}, "terminal_target": [1.0, 0.0]},
      "bounds": {"state": [-2.0, 2.0], "control": [-4.0, 4.0]},
      "constraints": [{"constraint_id": "dynamics_defect", "expression": "x[k+1]-x[k]-h*v[k]=0; v[k+1]-v[k]-h*u[k]=0", "sense": "eq"}, {"constraint_id": "terminal_target", "expression": "[x[N],v[N]]=[1,0]", "sense": "eq"}],
      "initialization_candidates": [{"candidate_id": "zero_trajectory", "point": [0.0]}],
      "seed_status": "fixed",
      "seed_value": 2026,
      "known_reference_status": "unknown",
      "known_reference": null,
      "display": {"range": {"time": [0.0, 1.0], "state_norm": [0.0, 2.0], "control_effort": [0.0, 8.0], "dynamics_defect": [0.0, 1.0], "path_violation": [0.0, 1.0], "objective_value": [0.0, 20.0]}, "axis_labels": ["normalized time", "diagnostic value"], "units": ["dimensionless", "normalized"], "expression": "min ∫(‖state‖²+0.01‖control‖²)dt with ẋ=v, v̇=u and terminal target [1,0]"},
      "intended_phenomena": ["trajectory_variable", "dynamics_defect", "path_constraint", "terminal_constraint", "mesh_refinement"],
      "limitations_ja": "20区間の固定meshによる教育用instanceです。連続時間の可行性・最適性、制御入力の実機安全性、solver family間の性能差を保証しません。",
      "limitations_en": "A fixed 20-interval educational instance; it does not establish continuous-time feasibility or optimality, physical actuator safety, or solver-family performance differences.",
      "source_ids": ["S042", "S043", "S050", "S076"],
      "last_verified": "2026-07-19"
    }
  ]
}
